python_house_package/__init__.py
python_house_package/allRoomsModule.py
python_house_package/connectorModule.py
python_house_package/connectorsModule.py
python_house_package/displayModule.py
python_house_package/floorModule.py
python_house_package/floorsModule.py
python_house_package/house.txt
python_house_package/houseDoor.gif
python_house_package/houseDoorClosed.gif
python_house_package/houseDoorOpen.gif
python_house_package/houseE.gif
python_house_package/houseN.gif
python_house_package/houseNext.gif
python_house_package/houseNotDoor.gif
python_house_package/houseNotDoorH.gif
python_house_package/houseNotDoorV.gif
python_house_package/houseOff.gif
python_house_package/houseS.gif
python_house_package/houseW.gif
python_house_package/main_house.py
python_house_package/personModule.py
python_house_package/roomModule.py
PythonHouse_ajhaigh6876-0.0.5.dist-info/LICENSE
PythonHouse_ajhaigh6876-0.0.5.dist-info/METADATA
PythonHouse_ajhaigh6876-0.0.5.dist-info/WHEEL
PythonHouse_ajhaigh6876-0.0.5.dist-info/top_level.txt
PythonHouse_ajhaigh6876-0.0.5.dist-info/RECORD
