Metadata-Version: 2.1
Name: PythonHouse-ajhaigh6876
Version: 0.0.5
Summary: A small example package
Home-page: https://github.com/pypa/sampleproject
Author: Andrew Haigh
Author-email: ajhaigh@yahoo.com
License: UNKNOWN
Project-URL: Bug Tracker, https://github.com/pypa/sampleproject/issues
Platform: UNKNOWN
Classifier: Programming Language :: Python :: 3
Classifier: License :: OSI Approved :: MIT License
Classifier: Operating System :: OS Independent
Requires-Python: >=3.6
License-File: LICENSE
Requires-Dist: appJar (==0.94.0)
